{"summaries":[{"symbol":{"__symbol":0,"members":[]},"metadata":{"__symbolic":"class"},"type":{"summaryKind":2,"type":{"reference":{"__symbol":0,"members":[]},"diDeps":[],"lifecycleHooks":[]},"entryComponents":[],"providers":[{"provider":{"token":{"identifier":{"reference":{"__symbol":1,"members":[]},"diDeps":[{"isAttribute":false,"isHost":false,"isSelf":false,"isSkipSelf":false,"isOptional":false,"token":{"identifier":{"reference":{"__symbol":2,"members":[]}}}}],"lifecycleHooks":[]}},"useClass":{"reference":{"__symbol":1,"members":[]},"diDeps":[{"isAttribute":false,"isHost":false,"isSelf":false,"isSkipSelf":false,"isOptional":false,"token":{"identifier":{"reference":{"__symbol":2,"members":[]}}}}],"lifecycleHooks":[]},"useFactory":null,"deps":[{"isAttribute":false,"isHost":false,"isSelf":false,"isSkipSelf":false,"isOptional":false,"token":{"identifier":{"reference":{"__symbol":2,"members":[]}}}}],"multi":false},"module":{"reference":{"__symbol":0,"members":[]},"diDeps":[],"lifecycleHooks":[]}},{"provider":{"token":{"identifier":{"reference":{"__symbol":3,"members":[]},"diDeps":[{"isAttribute":false,"isHost":false,"isSelf":false,"isSkipSelf":false,"isOptional":false,"token":{"identifier":{"reference":{"__symbol":1,"members":[]}}}},{"isAttribute":false,"isHost":false,"isSelf":false,"isSkipSelf":false,"isOptional":false,"token":{"identifier":{"reference":{"__symbol":4,"members":[]}}}},{"isAttribute":false,"isHost":false,"isSelf":false,"isSkipSelf":false,"isOptional":false,"token":{"identifier":{"reference":{"__symbol":5,"members":[]}}}}],"lifecycleHooks":[]}},"useClass":{"reference":{"__symbol":3,"members":[]},"diDeps":[{"isAttribute":false,"isHost":false,"isSelf":false,"isSkipSelf":false,"isOptional":false,"token":{"identifier":{"reference":{"__symbol":1,"members":[]}}}},{"isAttribute":false,"isHost":false,"isSelf":false,"isSkipSelf":false,"isOptional":false,"token":{"identifier":{"reference":{"__symbol":4,"members":[]}}}},{"isAttribute":false,"isHost":false,"isSelf":false,"isSkipSelf":false,"isOptional":false,"token":{"identifier":{"reference":{"__symbol":5,"members":[]}}}}],"lifecycleHooks":[]},"useFactory":null,"deps":[{"isAttribute":false,"isHost":false,"isSelf":false,"isSkipSelf":false,"isOptional":false,"token":{"identifier":{"reference":{"__symbol":1,"members":[]}}}},{"isAttribute":false,"isHost":false,"isSelf":false,"isSkipSelf":false,"isOptional":false,"token":{"identifier":{"reference":{"__symbol":4,"members":[]}}}},{"isAttribute":false,"isHost":false,"isSelf":false,"isSkipSelf":false,"isOptional":false,"token":{"identifier":{"reference":{"__symbol":5,"members":[]}}}}],"multi":false},"module":{"reference":{"__symbol":0,"members":[]},"diDeps":[],"lifecycleHooks":[]}},{"provider":{"token":{"identifier":{"reference":{"__symbol":6,"members":[]},"diDeps":[{"isAttribute":false,"isHost":false,"isSelf":false,"isSkipSelf":false,"isOptional":false,"token":{"identifier":{"reference":{"__symbol":1,"members":[]}}}},{"isAttribute":false,"isHost":false,"isSelf":false,"isSkipSelf":false,"isOptional":false,"token":{"identifier":{"reference":{"__symbol":4,"members":[]}}}}],"lifecycleHooks":[]}},"useClass":{"reference":{"__symbol":6,"members":[]},"diDeps":[{"isAttribute":false,"isHost":false,"isSelf":false,"isSkipSelf":false,"isOptional":false,"token":{"identifier":{"reference":{"__symbol":1,"members":[]}}}},{"isAttribute":false,"isHost":false,"isSelf":false,"isSkipSelf":false,"isOptional":false,"token":{"identifier":{"reference":{"__symbol":4,"members":[]}}}}],"lifecycleHooks":[]},"useFactory":null,"deps":[{"isAttribute":false,"isHost":false,"isSelf":false,"isSkipSelf":false,"isOptional":false,"token":{"identifier":{"reference":{"__symbol":1,"members":[]}}}},{"isAttribute":false,"isHost":false,"isSelf":false,"isSkipSelf":false,"isOptional":false,"token":{"identifier":{"reference":{"__symbol":4,"members":[]}}}}],"multi":false},"module":{"reference":{"__symbol":0,"members":[]},"diDeps":[],"lifecycleHooks":[]}},{"provider":{"token":{"identifier":{"reference":{"__symbol":7,"members":[]},"diDeps":[{"isAttribute":false,"isHost":false,"isSelf":false,"isSkipSelf":false,"isOptional":false,"token":{"identifier":{"reference":{"__symbol":1,"members":[]}}}},{"isAttribute":false,"isHost":false,"isSelf":false,"isSkipSelf":false,"isOptional":false,"token":{"identifier":{"reference":{"__symbol":4,"members":[]}}}}],"lifecycleHooks":[]}},"useClass":{"reference":{"__symbol":7,"members":[]},"diDeps":[{"isAttribute":false,"isHost":false,"isSelf":false,"isSkipSelf":false,"isOptional":false,"token":{"identifier":{"reference":{"__symbol":1,"members":[]}}}},{"isAttribute":false,"isHost":false,"isSelf":false,"isSkipSelf":false,"isOptional":false,"token":{"identifier":{"reference":{"__symbol":4,"members":[]}}}}],"lifecycleHooks":[]},"useFactory":null,"deps":[{"isAttribute":false,"isHost":false,"isSelf":false,"isSkipSelf":false,"isOptional":false,"token":{"identifier":{"reference":{"__symbol":1,"members":[]}}}},{"isAttribute":false,"isHost":false,"isSelf":false,"isSkipSelf":false,"isOptional":false,"token":{"identifier":{"reference":{"__symbol":4,"members":[]}}}}],"multi":false},"module":{"reference":{"__symbol":0,"members":[]},"diDeps":[],"lifecycleHooks":[]}},{"provider":{"token":{"identifier":{"reference":{"__symbol":8,"members":[]},"diDeps":[{"isAttribute":false,"isHost":false,"isSelf":false,"isSkipSelf":false,"isOptional":false,"token":{"identifier":{"reference":{"__symbol":1,"members":[]}}}},{"isAttribute":false,"isHost":false,"isSelf":false,"isSkipSelf":false,"isOptional":false,"token":{"identifier":{"reference":{"__symbol":4,"members":[]}}}}],"lifecycleHooks":[]}},"useClass":{"reference":{"__symbol":8,"members":[]},"diDeps":[{"isAttribute":false,"isHost":false,"isSelf":false,"isSkipSelf":false,"isOptional":false,"token":{"identifier":{"reference":{"__symbol":1,"members":[]}}}},{"isAttribute":false,"isHost":false,"isSelf":false,"isSkipSelf":false,"isOptional":false,"token":{"identifier":{"reference":{"__symbol":4,"members":[]}}}}],"lifecycleHooks":[]},"useFactory":null,"deps":[{"isAttribute":false,"isHost":false,"isSelf":false,"isSkipSelf":false,"isOptional":false,"token":{"identifier":{"reference":{"__symbol":1,"members":[]}}}},{"isAttribute":false,"isHost":false,"isSelf":false,"isSkipSelf":false,"isOptional":false,"token":{"identifier":{"reference":{"__symbol":4,"members":[]}}}}],"multi":false},"module":{"reference":{"__symbol":0,"members":[]},"diDeps":[],"lifecycleHooks":[]}},{"provider":{"token":{"identifier":{"reference":{"__symbol":9,"members":[]},"diDeps":[{"isAttribute":false,"isHost":false,"isSelf":false,"isSkipSelf":false,"isOptional":false,"token":{"identifier":{"reference":{"__symbol":1,"members":[]}}}},{"isAttribute":false,"isHost":false,"isSelf":false,"isSkipSelf":false,"isOptional":false,"token":{"identifier":{"reference":{"__symbol":4,"members":[]}}}}],"lifecycleHooks":[]}},"useClass":{"reference":{"__symbol":9,"members":[]},"diDeps":[{"isAttribute":false,"isHost":false,"isSelf":false,"isSkipSelf":false,"isOptional":false,"token":{"identifier":{"reference":{"__symbol":1,"members":[]}}}},{"isAttribute":false,"isHost":false,"isSelf":false,"isSkipSelf":false,"isOptional":false,"token":{"identifier":{"reference":{"__symbol":4,"members":[]}}}}],"lifecycleHooks":[]},"useFactory":null,"deps":[{"isAttribute":false,"isHost":false,"isSelf":false,"isSkipSelf":false,"isOptional":false,"token":{"identifier":{"reference":{"__symbol":1,"members":[]}}}},{"isAttribute":false,"isHost":false,"isSelf":false,"isSkipSelf":false,"isOptional":false,"token":{"identifier":{"reference":{"__symbol":4,"members":[]}}}}],"multi":false},"module":{"reference":{"__symbol":0,"members":[]},"diDeps":[],"lifecycleHooks":[]}},{"provider":{"token":{"identifier":{"reference":{"__symbol":10,"members":[]},"diDeps":[{"isAttribute":false,"isHost":false,"isSelf":false,"isSkipSelf":false,"isOptional":false,"token":{"identifier":{"reference":{"__symbol":1,"members":[]}}}},{"isAttribute":false,"isHost":false,"isSelf":false,"isSkipSelf":false,"isOptional":false,"token":{"identifier":{"reference":{"__symbol":4,"members":[]}}}}],"lifecycleHooks":[]}},"useClass":{"reference":{"__symbol":10,"members":[]},"diDeps":[{"isAttribute":false,"isHost":false,"isSelf":false,"isSkipSelf":false,"isOptional":false,"token":{"identifier":{"reference":{"__symbol":1,"members":[]}}}},{"isAttribute":false,"isHost":false,"isSelf":false,"isSkipSelf":false,"isOptional":false,"token":{"identifier":{"reference":{"__symbol":4,"members":[]}}}}],"lifecycleHooks":[]},"useFactory":null,"deps":[{"isAttribute":false,"isHost":false,"isSelf":false,"isSkipSelf":false,"isOptional":false,"token":{"identifier":{"reference":{"__symbol":1,"members":[]}}}},{"isAttribute":false,"isHost":false,"isSelf":false,"isSkipSelf":false,"isOptional":false,"token":{"identifier":{"reference":{"__symbol":4,"members":[]}}}}],"multi":false},"module":{"reference":{"__symbol":0,"members":[]},"diDeps":[],"lifecycleHooks":[]}},{"provider":{"token":{"identifier":{"reference":{"__symbol":10,"members":[]},"diDeps":[{"isAttribute":false,"isHost":false,"isSelf":false,"isSkipSelf":false,"isOptional":false,"token":{"identifier":{"reference":{"__symbol":1,"members":[]}}}},{"isAttribute":false,"isHost":false,"isSelf":false,"isSkipSelf":false,"isOptional":false,"token":{"identifier":{"reference":{"__symbol":4,"members":[]}}}}],"lifecycleHooks":[]}},"useClass":{"reference":{"__symbol":10,"members":[]},"diDeps":[{"isAttribute":false,"isHost":false,"isSelf":false,"isSkipSelf":false,"isOptional":false,"token":{"identifier":{"reference":{"__symbol":1,"members":[]}}}},{"isAttribute":false,"isHost":false,"isSelf":false,"isSkipSelf":false,"isOptional":false,"token":{"identifier":{"reference":{"__symbol":4,"members":[]}}}}],"lifecycleHooks":[]},"useFactory":null,"deps":[{"isAttribute":false,"isHost":false,"isSelf":false,"isSkipSelf":false,"isOptional":false,"token":{"identifier":{"reference":{"__symbol":1,"members":[]}}}},{"isAttribute":false,"isHost":false,"isSelf":false,"isSkipSelf":false,"isOptional":false,"token":{"identifier":{"reference":{"__symbol":4,"members":[]}}}}],"multi":false},"module":{"reference":{"__symbol":0,"members":[]},"diDeps":[],"lifecycleHooks":[]}},{"provider":{"token":{"identifier":{"reference":{"__symbol":11,"members":[]},"diDeps":[{"isAttribute":false,"isHost":false,"isSelf":false,"isSkipSelf":false,"isOptional":false,"token":{"identifier":{"reference":{"__symbol":1,"members":[]}}}},{"isAttribute":false,"isHost":false,"isSelf":false,"isSkipSelf":false,"isOptional":false,"token":{"identifier":{"reference":{"__symbol":4,"members":[]}}}}],"lifecycleHooks":[]}},"useClass":{"reference":{"__symbol":11,"members":[]},"diDeps":[{"isAttribute":false,"isHost":false,"isSelf":false,"isSkipSelf":false,"isOptional":false,"token":{"identifier":{"reference":{"__symbol":1,"members":[]}}}},{"isAttribute":false,"isHost":false,"isSelf":false,"isSkipSelf":false,"isOptional":false,"token":{"identifier":{"reference":{"__symbol":4,"members":[]}}}}],"lifecycleHooks":[]},"useFactory":null,"deps":[{"isAttribute":false,"isHost":false,"isSelf":false,"isSkipSelf":false,"isOptional":false,"token":{"identifier":{"reference":{"__symbol":1,"members":[]}}}},{"isAttribute":false,"isHost":false,"isSelf":false,"isSkipSelf":false,"isOptional":false,"token":{"identifier":{"reference":{"__symbol":4,"members":[]}}}}],"multi":false},"module":{"reference":{"__symbol":0,"members":[]},"diDeps":[],"lifecycleHooks":[]}},{"provider":{"token":{"identifier":{"reference":{"__symbol":12,"members":[]},"diDeps":[{"isAttribute":false,"isHost":false,"isSelf":false,"isSkipSelf":false,"isOptional":false,"token":{"identifier":{"reference":{"__symbol":1,"members":[]}}}},{"isAttribute":false,"isHost":false,"isSelf":false,"isSkipSelf":false,"isOptional":false,"token":{"identifier":{"reference":{"__symbol":4,"members":[]}}}}],"lifecycleHooks":[]}},"useClass":{"reference":{"__symbol":12,"members":[]},"diDeps":[{"isAttribute":false,"isHost":false,"isSelf":false,"isSkipSelf":false,"isOptional":false,"token":{"identifier":{"reference":{"__symbol":1,"members":[]}}}},{"isAttribute":false,"isHost":false,"isSelf":false,"isSkipSelf":false,"isOptional":false,"token":{"identifier":{"reference":{"__symbol":4,"members":[]}}}}],"lifecycleHooks":[]},"useFactory":null,"deps":[{"isAttribute":false,"isHost":false,"isSelf":false,"isSkipSelf":false,"isOptional":false,"token":{"identifier":{"reference":{"__symbol":1,"members":[]}}}},{"isAttribute":false,"isHost":false,"isSelf":false,"isSkipSelf":false,"isOptional":false,"token":{"identifier":{"reference":{"__symbol":4,"members":[]}}}}],"multi":false},"module":{"reference":{"__symbol":0,"members":[]},"diDeps":[],"lifecycleHooks":[]}},{"provider":{"token":{"identifier":{"reference":{"__symbol":13,"members":[]},"diDeps":[{"isAttribute":false,"isHost":false,"isSelf":false,"isSkipSelf":false,"isOptional":false,"token":{"identifier":{"reference":{"__symbol":1,"members":[]}}}},{"isAttribute":false,"isHost":false,"isSelf":false,"isSkipSelf":false,"isOptional":false,"token":{"identifier":{"reference":{"__symbol":4,"members":[]}}}}],"lifecycleHooks":[]}},"useClass":{"reference":{"__symbol":13,"members":[]},"diDeps":[{"isAttribute":false,"isHost":false,"isSelf":false,"isSkipSelf":false,"isOptional":false,"token":{"identifier":{"reference":{"__symbol":1,"members":[]}}}},{"isAttribute":false,"isHost":false,"isSelf":false,"isSkipSelf":false,"isOptional":false,"token":{"identifier":{"reference":{"__symbol":4,"members":[]}}}}],"lifecycleHooks":[]},"useFactory":null,"deps":[{"isAttribute":false,"isHost":false,"isSelf":false,"isSkipSelf":false,"isOptional":false,"token":{"identifier":{"reference":{"__symbol":1,"members":[]}}}},{"isAttribute":false,"isHost":false,"isSelf":false,"isSkipSelf":false,"isOptional":false,"token":{"identifier":{"reference":{"__symbol":4,"members":[]}}}}],"multi":false},"module":{"reference":{"__symbol":0,"members":[]},"diDeps":[],"lifecycleHooks":[]}},{"provider":{"token":{"identifier":{"reference":{"__symbol":14,"members":[]},"diDeps":[{"isAttribute":false,"isHost":false,"isSelf":false,"isSkipSelf":false,"isOptional":false,"token":{"identifier":{"reference":{"__symbol":1,"members":[]}}}},{"isAttribute":false,"isHost":false,"isSelf":false,"isSkipSelf":false,"isOptional":false,"token":{"identifier":{"reference":{"__symbol":4,"members":[]}}}}],"lifecycleHooks":[]}},"useClass":{"reference":{"__symbol":14,"members":[]},"diDeps":[{"isAttribute":false,"isHost":false,"isSelf":false,"isSkipSelf":false,"isOptional":false,"token":{"identifier":{"reference":{"__symbol":1,"members":[]}}}},{"isAttribute":false,"isHost":false,"isSelf":false,"isSkipSelf":false,"isOptional":false,"token":{"identifier":{"reference":{"__symbol":4,"members":[]}}}}],"lifecycleHooks":[]},"useFactory":null,"deps":[{"isAttribute":false,"isHost":false,"isSelf":false,"isSkipSelf":false,"isOptional":false,"token":{"identifier":{"reference":{"__symbol":1,"members":[]}}}},{"isAttribute":false,"isHost":false,"isSelf":false,"isSkipSelf":false,"isOptional":false,"token":{"identifier":{"reference":{"__symbol":4,"members":[]}}}}],"multi":false},"module":{"reference":{"__symbol":0,"members":[]},"diDeps":[],"lifecycleHooks":[]}},{"provider":{"token":{"identifier":{"reference":{"__symbol":15,"members":[]},"diDeps":[{"isAttribute":false,"isHost":false,"isSelf":false,"isSkipSelf":false,"isOptional":false,"token":{"identifier":{"reference":{"__symbol":1,"members":[]}}}},{"isAttribute":false,"isHost":false,"isSelf":false,"isSkipSelf":false,"isOptional":false,"token":{"identifier":{"reference":{"__symbol":4,"members":[]}}}}],"lifecycleHooks":[]}},"useClass":{"reference":{"__symbol":15,"members":[]},"diDeps":[{"isAttribute":false,"isHost":false,"isSelf":false,"isSkipSelf":false,"isOptional":false,"token":{"identifier":{"reference":{"__symbol":1,"members":[]}}}},{"isAttribute":false,"isHost":false,"isSelf":false,"isSkipSelf":false,"isOptional":false,"token":{"identifier":{"reference":{"__symbol":4,"members":[]}}}}],"lifecycleHooks":[]},"useFactory":null,"deps":[{"isAttribute":false,"isHost":false,"isSelf":false,"isSkipSelf":false,"isOptional":false,"token":{"identifier":{"reference":{"__symbol":1,"members":[]}}}},{"isAttribute":false,"isHost":false,"isSelf":false,"isSkipSelf":false,"isOptional":false,"token":{"identifier":{"reference":{"__symbol":4,"members":[]}}}}],"multi":false},"module":{"reference":{"__symbol":0,"members":[]},"diDeps":[],"lifecycleHooks":[]}}],"modules":[{"reference":{"__symbol":0,"members":[]},"diDeps":[],"lifecycleHooks":[]}],"exportedDirectives":[],"exportedPipes":[]}}],"symbols":[{"__symbol":0,"name":"ZgwnuBonitaModule","filePath":"/Users/onno/Documents/GIT/@zgwnu/ng-bonita/src/zgwnu-bonita.module.d.ts"},{"__symbol":1,"name":"ZgwnuBonitaConfigService","filePath":"/Users/onno/Documents/GIT/@zgwnu/ng-bonita/src/rest-api/zgwnu-bonita-config.service.d.ts"},{"__symbol":2,"name":"ZgwnuBonitaUrls","filePath":"/Users/onno/Documents/GIT/@zgwnu/ng-bonita/src/rest-api/zgwnu-bonita-urls.d.ts"},{"__symbol":3,"name":"ZgwnuBonitaAuthenticationService","filePath":"/Users/onno/Documents/GIT/@zgwnu/ng-bonita/src/authentication/zgwnu-bonita-authentication.service.d.ts"},{"__symbol":4,"name":"Http","filePath":"/Users/onno/Documents/GIT/@zgwnu/ng-bonita/src/node_modules/@angular/http/http.d.ts"},{"__symbol":5,"name":"Router","filePath":"/Users/onno/Documents/GIT/@zgwnu/ng-bonita/src/node_modules/@angular/router/router.d.ts"},{"__symbol":6,"name":"ZgwnuBonitaBpmProcessService","filePath":"/Users/onno/Documents/GIT/@zgwnu/ng-bonita/src/bpm/process/zgwnu-bonita-bpm-process.service.d.ts"},{"__symbol":7,"name":"ZgwnuBonitaBpmCaseService","filePath":"/Users/onno/Documents/GIT/@zgwnu/ng-bonita/src/bpm/case/zgwnu-bonita-bpm-case.service.d.ts"},{"__symbol":8,"name":"ZgwnuBonitaBpmCaseDocumentService","filePath":"/Users/onno/Documents/GIT/@zgwnu/ng-bonita/src/bpm/document/zgwnu-bonita-bpm-case-document.service.d.ts"},{"__symbol":9,"name":"ZgwnuBonitaBpmDataService","filePath":"/Users/onno/Documents/GIT/@zgwnu/ng-bonita/src/bpm/data/zgwnu-bonita-bpm-data.service.d.ts"},{"__symbol":10,"name":"ZgwnuBonitaBpmActivityService","filePath":"/Users/onno/Documents/GIT/@zgwnu/ng-bonita/src/bpm/activity/zgwnu-bonita-bpm-activity.service.d.ts"},{"__symbol":11,"name":"ZgwnuBonitaBpmTaskService","filePath":"/Users/onno/Documents/GIT/@zgwnu/ng-bonita/src/bpm/task/zgwnu-bonita-bpm-task.service.d.ts"},{"__symbol":12,"name":"ZgwnuBonitaBpmHumanTaskService","filePath":"/Users/onno/Documents/GIT/@zgwnu/ng-bonita/src/bpm/human-task/zgwnu-bonita-bpm-human-task.service.d.ts"},{"__symbol":13,"name":"ZgwnuBonitaBpmUserTaskService","filePath":"/Users/onno/Documents/GIT/@zgwnu/ng-bonita/src/bpm/user-task/zgwnu-bonita-bpm-user-task.service.d.ts"},{"__symbol":14,"name":"ZgwnuBonitaBusinessDataService","filePath":"/Users/onno/Documents/GIT/@zgwnu/ng-bonita/src/bdm/zgwnu-bonita-business-data.service.d.ts"},{"__symbol":15,"name":"ZgwnuBonitaFileUploadService","filePath":"/Users/onno/Documents/GIT/@zgwnu/ng-bonita/src/file-upload/zgwnu-bonita-file-upload.service.d.ts"}]}